{
  "timestamp": "2026-05-06T21:33:14.966386Z",
  "location": {
    "lat": 49.5,
    "lon": 8.46,
    "name": "Mannheim"
  },
  "verdict": {
    "score": 100,
    "label": "GEILO",
    "emoji": "🌌"
  },
  "kp": {
    "current": 3,
    "forecast": [
      3,
      4,
      3,
      2,
      1,
      2,
      3
    ]
  },
  "aurora": {
    "probability": 33,
    "hemisphere": "north"
  },
  "weather": {
    "cloud_cover": 15,
    "humidity": 62,
    "temperature": 8,
    "visibility": 25,
    "seeing": 2.1
  },
  "iss": {
    "lat": -43.94,
    "lon": -92.93,
    "altitude": 434.2,
    "velocity": 27543
  },
  "moon": {
    "phase": "waxing_gibbous",
    "illumination": 77,
    "rise": "23:14",
    "set": "07:26"
  },
  "meteors": [
    {
      "name": "Eta Aquariiden",
      "peak": "2026-05-06",
      "zhr": 50,
      "active": true
    }
  ]
}